{
  "items": {
    "banner": {
      "giveEffect": true,
      "showTooltip": true
    },
    "nutrition": {
      "cakeDoughNutrition": 5,
      "cakeDoughSaturationMod": 0.6,
      "sweetDoughNutrition": 5,
      "sweetDoughSaturationMod": 0.6,
      "croissantNutrition": 5,
      "croissantSaturationMod": 0.6,
      "crustyBreadNutrition": 5,
      "crustyBreadSaturationMod": 1.2,
      "breadNutrition": 5,
      "breadSaturationMod": 1.2,
      "baguetteNutrition": 5,
      "baguetteSaturationMod": 1.2,
      "toastNutrition": 3,
      "toastSaturationMod": 0.8,
      "braidedBreadNutrition": 5,
      "braidedBreadSaturationMod": 1.2,
      "sandwichNutrition": 7,
      "sandwichSaturationMod": 0.7,
      "vegetableSandwichNutrition": 8,
      "vegetableSandwichSaturationMod": 0.6,
      "grilledSalmonSandwichNutrition": 6,
      "grilledSalmonSandwichSaturationMod": 0.8,
      "grilledBaconSandwichNutrition": 7,
      "grilledBaconSandwichSaturationMod": 0.7,
      "breadWithJamNutrition": 5,
      "breadWithJamSaturationMod": 0.5,
      "strawberryCakeSliceNutrition": 5,
      "strawberryCakeSliceSaturationMod": 0.7,
      "sweetberryCakeSliceNutrition": 5,
      "sweetberryCakeSliceSaturationMod": 0.7,
      "chocolateCakeSliceNutrition": 5,
      "chocolateCakeSliceSaturationMod": 0.7,
      "chocolateGateauSliceNutrition": 5,
      "chocolateGateauSliceSaturationMod": 0.7,
      "bundtCakeSliceNutrition": 5,
      "bundtCakeSliceSaturationMod": 0.7,
      "linzerTartSliceNutrition": 5,
      "linzerTartSliceSaturationMod": 0.7,
      "applePieSliceNutrition": 5,
      "applePieSliceSaturationMod": 0.7,
      "glowberryPieSliceNutrition": 5,
      "glowberryPieSliceSaturationMod": 0.7,
      "chocolateTartSliceNutrition": 5,
      "chocolateTartSliceSaturationMod": 0.7,
      "puddingSliceNutrition": 5,
      "puddingSliceSaturationMod": 0.7,
      "strawberryGlazedCookieNutrition": 3,
      "strawberryGlazedCookieSaturationMod": 0.5,
      "sweetberryGlazedCookieNutrition": 3,
      "sweetberryGlazedCookieSaturationMod": 0.5,
      "chocolateGlazedCookieNutrition": 3,
      "chocolateGlazedCookieSaturationMod": 0.5,
      "strawberryCupcakeNutrition": 3,
      "strawberryCupcakeSaturationMod": 0.5,
      "sweetberryCupcakeNutrition": 3,
      "sweetberryCupcakeSaturationMod": 0.5,
      "appleCupcakeNutrition": 3,
      "appleCupcakeSaturationMod": 0.5,
      "cornetNutrition": 3,
      "cornetSaturationMod": 0.5,
      "jamRollNutrition": 3,
      "jamRollSaturationMod": 0.5,
      "waffleNutrition": 5,
      "waffleSaturationMod": 0.5,
      "chocolateTruffleNutrition": 2,
      "chocolateTruffleSaturationMod": 0.4,
      "misslilituBiscuitNutrition": 6,
      "misslilituBiscuitSaturationMod": 0.6,
      "bunNutrition": 5,
      "bunSaturationMod": 1.2
    }
  }
}